vibe_wf/__init__.py
vibe_wf/cli.py
vibe_wf/menu.py
vibe_wf/bundles/__init__.py
vibe_wf/bundles/v1/__init__.py
vibe_wf/bundles/v1/manifest.json
vibe_wf/bundles/v1/files/AGENTS.md
vibe_wf/bundles/v1/files/CLAUDE.md
vibe_wf/bundles/v1/files/opencode.jsonc
vibe_wf/bundles/v1/files/.claude/settings.json
vibe_wf/bundles/v1/files/.opencode/command/vibe/apply.md
vibe_wf/bundles/v1/files/.opencode/command/vibe/build.md
vibe_wf/bundles/v1/files/.opencode/command/vibe/help.md
vibe_wf/bundles/v1/files/.opencode/command/vibe/lint.md
vibe_wf/bundles/v1/files/.opencode/command/vibe/plan.md
vibe_wf/bundles/v1/files/.opencode/command/vibe/pwf-bootstrap.md
vibe_wf/bundles/v1/files/.opencode/command/vibe/review.md
vibe_wf/bundles/v1/files/.opencode/command/vibe/ship.md
vibe_wf/bundles/v1/files/.opencode/command/vibe/test.md
vibe_wf/bundles/v1/files/.vibe-wf/snippets/api/README.txt
vibe_wf/bundles/v1/files/.vibe-wf/snippets/mcp/README.txt
vibe_wf/bundles/v1/files/.vibe-wf/snippets/models/README.txt
vibe_wf/bundles/v1/files/docs/vibe-wf/AI_PROJECT_RUNBOOK.md
vibe_wf/bundles/v1/files/docs/vibe-wf/MCP_GUIDE.md
vibe_wf/bundles/v1/files/docs/vibe-wf/TOOLING.md
vibe_wf/bundles/v1/files/docs/vibe-wf/USAGE.md
vibe_wf/core/bundle.py
vibe_wf/core/engine.py
vibe_wf/core/fs.py
vibe_wf/core/hashing.py
vibe_wf/core/manifest.py
vibe_wf/core/paths.py
vibe_wf-0.1.0.dist-info/METADATA
vibe_wf-0.1.0.dist-info/WHEEL
vibe_wf-0.1.0.dist-info/entry_points.txt
vibe_wf-0.1.0.dist-info/RECORD
