Metadata-Version: 2.4
Name: vibe-wf
Version: 0.1.0
Summary: Project-local workflow bootstrap for OpenCode
Author-email: ljxpython <1030470148@qq.com>
Requires-Python: >=3.13
Requires-Dist: rich>=14.2.0
Requires-Dist: typer>=0.21.1
Provides-Extra: dev
Requires-Dist: pytest>=9.0.2; extra == 'dev'
